{
    "badini": {
        "backBtn": "زڤرن بۆ لاپەڕێ سەرەكي",
        "orderBtn": "كرین ب واتساپێ",
        "copyright": "© 2026 <strong>22 Show</strong>. گشت ماف پاراستینە.",
        "privacy": "سیاسەتا تایبەتەمەندیێ",
        "terms": "مەرجێن بكارهینانێ",
        "confirmBtn": "تەئكيدكرنا داخوازیێ",
        "sizeLabel": "قیاس / قەبارە:",
        "adminPanel": "پەنەلا ئەدمینان",
        "logout": "دەرکەفتن",
        "addProduct": "زێدەکرنا بەرهەمەکێ نی",
        "viewShop": "دیتنا فرۆشگەهێ",
        "productsList": "لیستا بەرهەمان",
        "edit": "دەستکاری",
        "delete": "ژێبرن",
        "save": "پاشکەوتکرن",
        "price": "بها:",
        "badge": "نیشان:",
        "type": "جۆر:",
        "galleryShowroom": "پێشانگەهـ و پێشانگەها کۆکراوەیان",
        "deliveryInfo": "کاردکەین ل هەرێما کوردستانێ دگەل گەهاندنێ بۆ هەمی عێراقێ.",
        "saveContact": "پاشکەوتکرنا ژمارێ"
    },
    "sorani": {
        "backBtn": "گەڕانەوە بۆ لاپەڕەی سەرەکی",
        "orderBtn": "داواکردن بە واتساپ",
        "copyright": "© 2026 <strong>22 Show</strong>. گشتی مافەکان پارێزراون.",
        "privacy": "سیاسەتی تایبەتێتی",
        "terms": "مەرجەکانی بەکارهێنان",
        "confirmBtn": "پشتڕاستکردنەوەی داواکاری",
        "sizeLabel": "قەبارە:",
        "adminPanel": "پەناڵی ئەدمینان",
        "logout": "چوونە دەرەوە",
        "addProduct": "زیادکردنی بەرهەمێکی نوێ",
        "viewShop": "بینینی فرۆشگا",
        "productsList": "لیستی بەرهەمەکان",
        "edit": "دەستکاری",
        "delete": "سڕینەوە",
        "save": "پاشەکەوتکردن",
        "price": "نرخ:",
        "badge": "نیشانە:",
        "type": "جۆر:",
        "galleryShowroom": "پێشانگا و پێشانگای کۆکراوەکان",
        "deliveryInfo": "لە هەرێمی کوردستانەوە کاردەکرێت لەگەڵ گەیاندن بۆ سەرتاسەری عێراق.",
        "saveContact": "هەڵگرتنی ژمارە"
    },
    "arabic": {
        "backBtn": "العودة للرئيسية",
        "orderBtn": "اطلب عبر واتساب",
        "copyright": "© 2026 <strong>22 Show</strong>. جميع الحقوق محفوظة.",
        "privacy": "سياسة الخصوصية",
        "terms": "شروط الخدمة",
        "confirmBtn": "تأكيد الطلب وإرسال",
        "sizeLabel": "المقاس:",
        "adminPanel": "لوحة الإدارة",
        "logout": "تسجيل الخروج",
        "addProduct": "إضافة منتج جديد",
        "viewShop": "عرض المتجر",
        "productsList": "قائمة المنتجات",
        "edit": "تعديل",
        "delete": "حذف",
        "save": "حفظ",
        "price": "السعر:",
        "badge": "الشارة:",
        "type": "النوع:",
        "galleryShowroom": "معرض التشكيلة وصالة العرض",
        "deliveryInfo": "نعمل من إقليم كردستان مع توفر التوصيل لجميع أنحاء العراق.",
        "saveContact": "حفظ جهة الاتصال"
    },
    "english": {
        "backBtn": "Back to Home",
        "orderBtn": "Order via WhatsApp",
        "copyright": "© 2026 <strong>22 Show</strong>. All rights reserved.",
        "privacy": "Privacy Policy",
        "terms": "Terms of Service",
        "confirmBtn": "Confirm Order",
        "sizeLabel": "Size:",
        "adminPanel": "Admin Panel",
        "logout": "Logout",
        "addProduct": "Add New Product",
        "viewShop": "View Shop",
        "productsList": "Products List",
        "edit": "Edit",
        "delete": "Delete",
        "save": "Save",
        "price": "Price:",
        "badge": "Badge:",
        "type": "Type:",
        "galleryShowroom": "Collection Gallery & Showroom",
        "deliveryInfo": "Operating from the Kurdistan Region with delivery across Iraq.",
        "saveContact": "Save Contact"
    }
}
